BIRs/__init__.py
BIRs/libs.py
basic_influence_roles-1.0.5.dist-info/METADATA
basic_influence_roles-1.0.5.dist-info/WHEEL
basic_influence_roles-1.0.5.dist-info/top_level.txt
basic_influence_roles-1.0.5.dist-info/RECORD
