Metadata-Version: 2.1
Name: basic-influence-roles
Version: 1.0.5
Summary: Detect and measure the Basic Influence Role each node holds within a Directed Network.
Author: Davide Miceli
Maintainer: Davide Miceli
Project-URL: Homepage, https://github.com/davidemiceli/basic-influence-roles
Project-URL: Issues, https://github.com/davidemiceli/basic-influence-roles/issues
Keywords: graph,network,clustering,complex networks,network analysis,social network analysis,network science,influence network,network dynamics,social influence,social role,social sciences
Classifier: Programming Language :: Python :: 3
Classifier: License :: OSI Approved :: MIT License
Classifier: Operating System :: OS Independent
Classifier: Development Status :: 5 - Production/Stable
Classifier: Topic :: Scientific/Engineering :: Information Analysis
Classifier: Topic :: Scientific/Engineering :: Mathematics
Classifier: Topic :: Sociology
Classifier: Topic :: Software Development :: Libraries :: Python Modules
Classifier: Intended Audience :: Developers
Classifier: Intended Audience :: Information Technology
Classifier: Intended Audience :: Science/Research
Requires-Python: >=3.0
Provides-Extra: dev
Requires-Dist: coverage ; extra == 'dev'
Requires-Dist: networkx ; extra == 'dev'
